src/__init__.py
src/yt_pld.py
YouTubeUploader-0.0.3.dist-info/METADATA
YouTubeUploader-0.0.3.dist-info/WHEEL
YouTubeUploader-0.0.3.dist-info/top_level.txt
YouTubeUploader-0.0.3.dist-info/RECORD
