Metadata-Version: 2.1
Name: YouTubeUploader
Version: 0.0.3
Summary: Uploading videos to YouTube
Author: [{'name': 'David', 'email': 'david2002belozerov@mail.ru'}]
Author-email: David <david2002belozerov@mail.ru>
Requires-Python: >=3.8
Requires-Dist: selenium ==4.16.0
